streak/__init__.py
streak/streak.py
streak/version.py
python_streak-1.0.0.dist-info/LICENSE
python_streak-1.0.0.dist-info/METADATA
python_streak-1.0.0.dist-info/WHEEL
python_streak-1.0.0.dist-info/entry_points.txt
python_streak-1.0.0.dist-info/top_level.txt
python_streak-1.0.0.dist-info/RECORD
